hfttools/__init__.py
hfttools/core.py
hfttools-0.0.2.dist-info/DESCRIPTION.rst
hfttools-0.0.2.dist-info/METADATA
hfttools-0.0.2.dist-info/RECORD
hfttools-0.0.2.dist-info/WHEEL
hfttools-0.0.2.dist-info/metadata.json
hfttools-0.0.2.dist-info/top_level.txt
