Metadata-Version: 2.0
Name: hfttools
Version: 0.0.2
Summary: A package for high-frequency trade research.
Home-page: https://github.com/colinswaney/hfttools
Author: Colin Swaney
Author-email: colin-swaney@uiowa.edu
License: The MIT License (MIT)
Requires-Dist: h5py
Requires-Dist: numpy
Requires-Dist: pandas
Requires-Dist: psycopg2
